lazyqyweixin/__init__.py
lazyqyweixin/internal_app.py
lazyqyweixin-0.0.9.dist-info/METADATA
lazyqyweixin-0.0.9.dist-info/WHEEL
lazyqyweixin-0.0.9.dist-info/top_level.txt
lazyqyweixin-0.0.9.dist-info/RECORD
