Metadata-Version: 2.1
Name: lazyqyweixin
Version: 0.0.9
Summary: 企业微信接口封装
Home-page: https://gitee.com/ZeroSeeker/lazyqyweixin
Author: ZeroSeeker
Author-email: zeroseeker@foxmail.com
Classifier: Programming Language :: Python :: 3
Classifier: Operating System :: OS Independent
Requires-Dist: lazysdk >=0.1.88
Requires-Dist: chardet ==5.2.0
